seiscat/__init__.py
seiscat/_version.py
seiscat/db.py
seiscat/download_event_details.py
seiscat/download_event_waveforms.py
seiscat/editdb.py
seiscat/fdsnws.py
seiscat/feeddb.py
seiscat/parse_arguments.py
seiscat/plot_map.py
seiscat/plot_map_cartopy.py
seiscat/plot_map_folium.py
seiscat/plot_map_utils.py
seiscat/print.py
seiscat/utils.py
seiscat/conf/configspec.conf
seiscat/configobj/LICENSE
seiscat/configobj/__init__.py
seiscat/configobj/_version.py
seiscat/configobj/validate.py
seiscat/scripts/seiscat.py
seiscat-0.8.dist-info/LICENSE.txt
seiscat-0.8.dist-info/METADATA
seiscat-0.8.dist-info/WHEEL
seiscat-0.8.dist-info/entry_points.txt
seiscat-0.8.dist-info/top_level.txt
seiscat-0.8.dist-info/RECORD
