Metadata-Version: 2.1
Name: seiscat
Version: 0.8
Summary: Keep a local seismic catalog
Author-email: Claudio Satriano <satriano@ipgp.fr>
License: GNU General Public License v3 or later (GPLv3+)
Project-URL: Homepage, https://seiscat.seismicsource.org
Project-URL: Source, https://github.com/SeismicSource/seiscat
Project-URL: Documentation, https://seiscat.readthedocs.io
Platform: OS
Platform: Independent
Classifier: Development Status :: 4 - Beta
Classifier: Environment :: Console
Classifier: Intended Audience :: Science/Research
Classifier: License :: OSI Approved :: GNU General Public License v3 or later (GPLv3+)
Classifier: Operating System :: OS Independent
Classifier: Programming Language :: Python
Classifier: Programming Language :: Python :: 3
Classifier: Programming Language :: Python :: 3.7
Classifier: Programming Language :: Python :: 3.8
Classifier: Programming Language :: Python :: 3.9
Classifier: Programming Language :: Python :: 3.10
Classifier: Programming Language :: Python :: 3.11
Classifier: Programming Language :: Python :: 3.12
Classifier: Topic :: Scientific/Engineering
Classifier: Topic :: Scientific/Engineering :: Physics
Requires-Python: >=3.7
License-File: LICENSE.txt
Requires-Dist: obspy >=1.2.0
Requires-Dist: argcomplete
